<?xml version="1.0" encoding="UTF-8" standalone="yes"?>
<CentraXXDataExchange
    xmlns="http://www.kairos-med.de"
    xmlns:xsi="http://www.w3.org/2001/XMLSchema-instance" xsi:schemaLocation="http://www.kairos-med.de ../CentraXXExchange.xsd">
  <Source>CENTRAXX</Source>
  <SourceVersion>2022.3.0-SNAPSHOT</SourceVersion>
  <ExportDate>2022-09-16T16:58:21.130+02:00</ExportDate>
  <CatalogueData>
    <UnityCatalogueItem>
      <NameMultilingualEntries>
        <Lang>de</Lang>
        <Value>per minute</Value>
      </NameMultilingualEntries>
      <NameMultilingualEntries>
        <Lang>en</Lang>
        <Value>(en) - /min</Value>
      </NameMultilingualEntries>
      <Code>PER_MINUTE</Code>
      <Used>false</Used>
      <SyncId>b217f19c-0f5e-4e1f-a46a-d64ef1b369a4</SyncId>
    </UnityCatalogueItem>
    <FlexibleValueCatalogueItem>
      <FlexibleDecimalValue>
        <Code>HEART_RATE</Code>
        <NameMultilingualEntries>
          <Lang>en</Lang>
          <Value>Heart Rate</Value>
        </NameMultilingualEntries>
        <NameMultilingualEntries>
          <Lang>de</Lang>
          <Value>Herzrate</Value>
        </NameMultilingualEntries>
        <SyncId>cc1fc6fd-9f46-4dc8-8230-ff55c662f303</SyncId>
        <LaborValueGroupRef RefUrl="/rest/export/catalogdata/LaborValueGroup/53" DisplayName="US Core Vital Signs">US_CORE_VITAL_SIGNS</LaborValueGroupRef>
        <UserEntries>
          <Systemwide>true</Systemwide>
        </UserEntries>
        <LaborValueIDContainer>
          <FlexibleID isUpdateAllowed="false">
            <key>LOINC</key>
            <value>8867-4</value>
          </FlexibleID>
          <FlexibleID isUpdateAllowed="false">
            <key>US_CORE_FHIR_EXPORT_DISCRIMINATOR</key>
            <value>US_CORE_VITAL_SIGNS</value>
          </FlexibleID>
        </LaborValueIDContainer>
        <LowerPrecision>CLOSED</LowerPrecision>
        <UpperPrecision>CLOSED</UpperPrecision>
        <UnitTypeRef RefUrl="/rest/export/catalogdata/Unity/30" DisplayName="per minute">PER_MINUTE</UnitTypeRef>
      </FlexibleDecimalValue>
    </FlexibleValueCatalogueItem>
    <FlexibleDataSetCatalogueItem>
      <Code>US_CORE_HEART_RATE</Code>
      <NameMultilingualEntries>
        <Lang>de</Lang>
        <Value>US Core Herzrate</Value>
      </NameMultilingualEntries>
      <NameMultilingualEntries>
        <Lang>en</Lang>
        <Value>US Core Heart Rate</Value>
      </NameMultilingualEntries>
      <FlexibleValueComplexRefs>
        <FlexibleValueRef RefUrl="/rest/export/catalogdata/LaborValueDecimal/257" DisplayName="Herzrate">HEART_RATE</FlexibleValueRef>
        <Required>false</Required>
      </FlexibleValueComplexRefs>
      <Systemwide>true</Systemwide>
      <FlexibleDataSetType>MEASUREMENT</FlexibleDataSetType>
      <Category>VITALSIGN</Category>
      <CrfTemplateRef RefUrl="/rest/export/catalogdata/CrfTemplate/214">
        <Name>US Core Herzrate</Name>
        <Version>0</Version>
        <SyncId>b8c12199-bef9-4982-a3e5-e4711af2d2a4</SyncId>
      </CrfTemplateRef>
      <Version>1</Version>
      <SyncId>6d9c4d4b-49a7-484f-9a94-a7b07048484c</SyncId>
    </FlexibleDataSetCatalogueItem>
    <CrfTemplate>
      <Name>US Core Herzrate</Name>
      <CrfTemplateSection>
        <Name>HEART_RATE</Name>
        <NameMultilingualEntries>
          <Lang>en</Lang>
          <Value>Heart Rate</Value>
        </NameMultilingualEntries>
        <NameMultilingualEntries>
          <Lang>de</Lang>
          <Value>Herzrate</Value>
        </NameMultilingualEntries>
        <Code>HEART_RATE</Code>
        <CrfTemplateField>
          <LaborValue RefUrl="/rest/export/catalogdata/LaborValueDecimal/257" DisplayName="Herzrate">HEART_RATE</LaborValue>
          <LowerRow>0</LowerRow>
          <LowerColumn>0</LowerColumn>
          <UpperRow>0</UpperRow>
          <UpperColumn>0</UpperColumn>
          <Mandatory>false</Mandatory>
          <VisibleCaption>true</VisibleCaption>
          <FieldType>LABORVALUE</FieldType>
          <TabIndex>0</TabIndex>
          <ReadOnly>false</ReadOnly>
          <Pseudomized>false</Pseudomized>
          <OnsetEvent>false</OnsetEvent>
          <CreateContactAddressAllowed>false</CreateContactAddressAllowed>
          <MultilingualValueAllowed>false</MultilingualValueAllowed>
          <SyncId>34b701f4-611f-4ffb-8fbd-1b3dd0920ac0</SyncId>
        </CrfTemplateField>
        <Height>1</Height>
        <Width>1</Width>
        <Position>0</Position>
        <CrfSectionType>PLAIN</CrfSectionType>
        <IsChangeable>true</IsChangeable>
        <SyncId>bc8c4415-777a-4d8e-90bd-22e515112efd</SyncId>
      </CrfTemplateSection>
      <TemplateType>LABORMETHOD</TemplateType>
      <Version>0</Version>
      <EntityStatus>ACTIVE</EntityStatus>
      <Global>false</Global>
      <MultipleUse>false</MultipleUse>
      <Active>false</Active>
      <SyncId>b8c12199-bef9-4982-a3e5-e4711af2d2a4</SyncId>
    </CrfTemplate>
    <LaborValueGroup>
      <Code>US_CORE_VITAL_SIGNS</Code>
      <NameMultilingualEntries>
        <Lang>en</Lang>
        <Value>US Core Vital Signs</Value>
      </NameMultilingualEntries>
      <NameMultilingualEntries>
        <Lang>de</Lang>
        <Value>US Core Vital Signs</Value>
      </NameMultilingualEntries>
      <SyncId>98988d19-d4bd-4870-afc2-a3c8c73573ce</SyncId>
    </LaborValueGroup>
  </CatalogueData>
  <EffectData/>
</CentraXXDataExchange>
